{
  "project_info": {
    "project_number": "359903799647",
    "project_id": "eazzy-store",
    "storage_bucket": "eazzy-store.firebasestorage.app"
  },
  "client": [
    {
      "client_info": {
        "mobilesdk_app_id": "1:359903799647:android:3c5bc8a1b33d938f98aeea",
        "android_client_info": {
          "package_name": "com.eazzybusiness.app"
        }
      },
      "oauth_client": [],
      "api_key": [
        {
          "current_key": "AIzaSyBBDHRI7PMPgyENBqVpjrbNOu_3fiAeC6c"
        }
      ],
      "services": {
        "appinvite_service": {
          "other_platform_oauth_client": []
        }
      }
    }
  ],
  "configuration_version": "1"
}